clickset/__init__.py
clickset/config.py
clickset/setting.py
clickset-1.1.0.dist-info/LICENSE.txt
clickset-1.1.0.dist-info/METADATA
clickset-1.1.0.dist-info/WHEEL
clickset-1.1.0.dist-info/RECORD
