Metadata-Version: 2.1
Name: clickset
Version: 1.1.0
Summary: In-class settings configurable via both click and confuse libraries
Home-page: https://gitlab.com/selcouth/clickset
License: MIT
Author: David Morris
Author-email: gypsysoftware@gmail.com
Requires-Python: >=3.10,<4.0
Classifier: License :: OSI Approved :: MIT License
Classifier: Programming Language :: Python :: 3
Classifier: Programming Language :: Python :: 3.10
Classifier: Programming Language :: Python :: 3.11
Classifier: Programming Language :: Python :: 3.12
Requires-Dist: click (>=8.1.7,<9.0.0)
Requires-Dist: confuse (>=2.0.1,<3.0.0)
Project-URL: Repository, https://gitlab.com/selcouth/clickset
